Workbook

Sheet BacchaX
A1: Income
A2: ID Number | B2: First name | C2: Last Name | D2: Age | E2: Gender | F2: Address | G2: Phone Number | H2: Costume Payment Option | I2: Full Payment | J2: Installments | M2: Inclusive Fee Option | O2: Total Costume Amount | P2: Total Payment in USD | Q2: Total Payment in JMD
A3: 27612 | B3: Emily | C3: Johnston | D3: 29 | E3: Female | F3: 231 Apple Street | G3: (876) 253-2858 | H3: Installment | I3: - | J3: 53.33 | K3: 53.33 | L3: 53.33 | M3: Full | N3: 150 | O3: =SUM(I3:L3) -> 159.99 | P3: =O3+(O3*$T$4)+N3 -> 333.9885 | Q3: =P3*$T$6 -> 51738.159
A4: 47423 | B4: Emma | C4: brown | D4: 25 | E4: Female | F4: 342 Church Lane | G4: (876) 338-9391 | H4: Installment | I4: - | J4: 53.33 | K4: 53.33 | L4: 53.33 | M4: Full | N4: 150 | O4: =SUM(I4:L4) -> 159.99 | P4: =O4+(O4*$T$4)+N4 -> 333.9885 | Q4: =P4*$T$6 -> 51738.159 | S4: Interest | T4: 0.15
A5: 24246 | B5: Stefene | C5: Wiliams | D5: 21 | E5: Female | F5: 879 Pineappl Road | G5: (876) 738-4999 | H5: Single Payment | I5: 160 | J5: - | K5: - | L5: - | M5: Full | N5: 150 | O5: =SUM(I5:L5) -> 160 | P5: =O5-(O5*$T$5)+N5 -> 294 | Q5: =P5*$T$6 -> 45543.54 | S5: Discount | T5: 0.1
A6: 73754 | B6: bella | C6: Taylor | D6: 31 | E6: Female | F6: 890 Will Drive | G6: (876) 368-9380 | H6: Single Payment | I6: 160 | J6: - | K6: - | L6: - | M6: Full | N6: 150 | O6: =SUM(I6:L6) -> 160 | P6: =O6-(O6*$T$5)+N6 -> 294 | Q6: =P6*$T$6 -> 45543.54 | S6: JMD Equivalent | T6: 154.91
A7: 34545 | B7: Will | C7: Wilson | D7: 37 | E7: Male | F7: 878 Ashley Street | G7: (876) 503-9395 | H7: Single Payment | I7: 160 | J7: - | K7: - | L7: - | M7: Full | N7: 150 | O7: =SUM(I7:L7) -> 160 | P7: =O7-(O7*$T$5)+N7 -> 294 | Q7: =P7*$T$6 -> 45543.54
A8: 64667 | B8: Mimi | C8: Hernandez | D8: 24 | E8: Female | F8: 748 Pirch Lane | G8: (876) 332-9396 | H8: Single Payment | I8: 160 | J8: - | K8: - | L8: - | M8: Full | N8: 150 | O8: =SUM(I8:L8) -> 160 | P8: =O8-(O8*$T$5)+N8 -> 294 | Q8: =P8*$T$6 -> 45543.54
A9: 45667 | B9: Alex | C9: Lopez | D9: 31 | E9: Male | F9: 676 Symone Street | G9: (876) 388-9397 | H9: Single Payment | I9: 160 | J9: - | K9: - | L9: - | M9: Full | N9: 150 | O9: =SUM(I9:L9) -> 160 | P9: =O9-(O9*$T$5)+N9 -> 294 | Q9: =P9*$T$6 -> 45543.54
A10: 34335 | B10: mike | C10: Smith | D10: 36 | E10: Male | F10: 476 Oakland drive | G10: (876) 756-4851 | H10: Installment | I10: - | J10: 53.33 | K10: - | L10: - | M10: Full | N10: 150 | O10: =SUM(I10:L10) -> 53.33 | P10: =O10+(O10*$T$4)+N10 -> 211.3295 | Q10: =P10*$T$6 -> 32737.053
A11: 23834 | B11: Jake | C11: Davis | D11: 35 | E11: Male | F11: 756 Bull Boluevard | G11: (876) 378-9389 | H11: Installment | I11: - | J11: 53.33 | K11: - | L11: - | M11: Full | N11: 150 | O11: =SUM(I11:L11) -> 53.33 | P11: =O11+(O11*$T$4)+N11 -> 211.3295 | Q11: =P11*$T$6 -> 32737.053
A12: 65629 | B12: Benny | C12: Brown | D12: 41 | E12: Male | F12: 101 Elm street | G12: (876) 948-3957 | H12: Single Payment | I12: 160 | J12: - | K12: - | L12: - | M12: Partial | N12: 50 | O12: =SUM(I12:L12) -> 160 | P12: =O12-(O12*$T$5)+N12 -> 194 | Q12: =P12*$T$6 -> 30052.54
A13: 55434 | B13: Oliv | C13: Jones | D13: 27 | E13: Female | F13: 647 Cox Street | G13: (876) 378-9388 | H13: Single Playment | I13: 160 | J13: - | K13: - | L13: - | M13: Partial | N13: 50 | O13: =SUM(I13:L13) -> 160 | P13: =O13-(O13*$T$5)+N13 -> 194 | Q13: =P13*$T$6 -> 30052.54
A14: 25202 | B14: Angle | C14: Lopez | D14: 40 | E14: Female | F14: 56 Cordelia Drive | G14: (876) 586-9564 | H14: Single Payment | I14: 160 | J14: - | K14: - | L14: - | M14: Partial | N14: 50 | O14: =SUM(I14:L14) -> 160 | P14: =O14-(O14*$T$5)+N14 -> 194 | Q14: =P14*$T$6 -> 30052.54
A15: 56559 | B15: Charlie | C15: Gonzalez | D15: 26 | E15: Female | F15: 263 Maple road | G15: (876) 238-9398 | H15: Installment | I15: - | J15: 53.33 | K15: 53.33 | L15: - | M15: Partial | N15: 50 | O15: =SUM(I15:L15) -> 106.66 | P15: =O15+(O15*$T$4)+N15 -> 172.659 | Q15: =P15*$T$6 -> 26746.606
A16: 45565 | B16: Eugene | C16: Garcia | D16: 32 | E16: Male | F16: 435 Spence Avenue | G16: (876) 434-2346 | H16: Installment | I16: - | J16: 53.33 | K16: - | L16: - | M16: Partial | N16: 50 | O16: =SUM(I16:L16) -> 53.33 | P16: =O16+(O16*$T$4)+N16 -> 111.3295 | Q16: =P16*$T$6 -> 17246.053
A17: 31243 | B17: Matt | C17: Martinez | D17: 38 | E17: Male | F17: 121 Magnolia provence | G17: (876) 336-9391 | H17: Installment | I17: - | J17: - | K17: - | L17: - | M17: Partial | N17: 50 | O17: =SUM(I17:L17) -> 0 | P17: =O17+(O17*$T$4)+N17 -> 50 | Q17: =P17*$T$6 -> 7745.5
A18: 35568 | B18: Eva | C18: Rodriquez | D18: 28 | E18: Female | F18: 116 Walnut drive | G18: (876) 284-9394 | H18: Installment | I18: - | J18: - | K18: - | L18: - | M18: Partial | N18: 50 | O18: =SUM(I18:L18) -> 0 | P18: =O18+(O18*$T$4)+N18 -> 50 | Q18: =P18*$T$6 -> 7745.5
A21: No. of Masqueraders | C21: =COUNT(A4:A19) -> 15 | O21: Total Payment Collected | P21: =SUM(P4:P19) -> 3192.636 | Q21: =SUM(Q4:Q19) -> 494571.24
A22: Total Costume Payment | C22: =SUM(O4:O19) -> 1706.64
A23: Total Inclusive Fee | C23: =SUMIF(N4:N19,"=150") -> 1200
A24: Total Overall Payment | C24: =SUM(P4:P19) -> 3192.636
A26: EXPENDITURE
A27: Service | B27: Cost Per Person | C27: Flat Rate | D27: Service Interest | E27: Total Cost | F27: Total Cost per Service
A28: Food | B28: 60 | C28: - | D28: 0.15 | E28: =B28 -> 60 | F28: =PRODUCT(E28*$C$21) -> 900
A29: Drink | B29: 40 | C29: - | D29: 0.15 | E29: =B29 -> 40 | F29: =PRODUCT(E29*$C$21) -> 600
A30: Material | B30: 135 | C30: - | D30: 0.12 | E30: =B30 -> 135 | F30: =PRODUCT(E30*$C$21) -> 2025
A31: Labour | B31: 95 | C31: - | D31: 0.08 | E31: =B31 -> 95 | F31: =PRODUCT(E31*$C$21) -> 1425
A32: Bathroom | B32: - | C32: 3000 | D32: - | E32: =C32/5 -> 600 | F32: =PRODUCT(E32,15) -> 9000
A33: Transort | B33: - | C33: 2500 | D33: - | E33: =C33/5 -> 500 | F33: =PRODUCT(E33,15) -> 7500
A34: Music | B34: - | C34: 4000 | D34: - | E34: =C34/5 -> 800 | F34: =PRODUCT(E34,15) -> 12000
A35: Security | B35: - | C35: 1800 | D35: - | E35: =C35/5 -> 360 | F35: =PRODUCT(E35,15) -> 5400
A36: Artiste | B36: - | C36: 5000 | D36: - | E36: =C36/5 -> 1000 | F36: =PRODUCT(E36,15) -> 15000
E38: Total Expenditure | F38: =SUM(F28:F36) -> 53850
A40: Section Name | B40: Total Income | C40: Total Expenditure
A41: BacchaX | B41: =Q21 -> 494571.24 | C41: =F38 -> 53850
A42: Xod-Us | B42: ='Xod-Us'!Q21 -> 587258.47 | C42: ='Xod-Us'!F38 -> 54183
A43: JamCarm X | B43: ='JamCarn X'!Q20 -> 816988.52 | C43: ='JamCarn X'!F37 -> 54912.36
A44: Fant-X | B44: ='Fant-X'!Q18 -> 849396.32 | C44: ='Fant-X'!F35 -> 55754.155
A45: DreamX | B45: =DreamX!Q18 -> 1018096.4 | C45: =DreamX!F35 -> 56727.327

Sheet Xod-Us
A1: Income
A2: ID Number | B2: First name | C2: Last Name | D2: Age | E2: Gender | F2: Address | G2: Phone Number | H2: Costume Payment Option | I2: Full Payment | J2: Installments | M2: Inclusive Fee Option | O2: Total Costume Amount | P2: Total Payment in USD | Q2: Total Payment in JMD
A3: 62501 | B3: Damian | C3: Davis | D3: 19 | E3: Male | F3: 567 Birch Drive, Meadowbrook | G3: (876) 314-1572 | H3: Installment | I3: - | J3: 73.33 | K3: 73.33 | L3: 73.33 | M3: Full | N3: 150 | O3: =SUM(I3:L3) -> 219.99 | P3: =O3+(O3*$T$4)+N3 -> 402.9885 | Q3: =P3*$T$6 -> 62426.949
A4: 75248 | B4: ackeem | C4: Allen | D4: 33 | E4: Male | F4: 13 Stennett Street | G4: (876) 856-8757 | H4: Installment | I4: - | J4: 73.33 | K4: 73.33 | L4: 73.33 | M4: Full | N4: 150 | O4: =SUM(I4:L4) -> 219.99 | P4: =O4+(O4*$T$4)+N4 -> 402.9885 | Q4: =P4*$T$6 -> 62426.949 | S4: Interest | T4: 0.15
A5: 83947 | B5: Evan | C5: Smith | D5: 24 | E5: Female | F5: 123 Maple Street, Springfield | G5: (876) 839-2057 | H5: Single Payment | I5: 220 | J5: - | K5: - | L5: - | M5: Full | N5: 150 | O5: =SUM(I5:L5) -> 220 | P5: =O5-(O5*$T$5)+N5 -> 348 | Q5: =P5*$T$6 -> 53908.68 | S5: Discount | T5: 0.1
A6: 58024 | B6: Eddie | C6: Taylor | D6: 39 | E6: Male | F6: 678 Pinecrest Road, Mountain View | G6: (876) 830-7596 | H6: Single Payment | I6: 220 | J6: - | K6: - | L6: - | M6: Full | N6: 150 | O6: =SUM(I6:L6) -> 220 | P6: =O6-(O6*$T$5)+N6 -> 348 | Q6: =P6*$T$6 -> 53908.68 | S6: JMD Equivalent | T6: 154.91
A7: 72035 | B7: allen | C7: White | D7: 47 | E7: Male | F7: 1515 Cedar Lane, Hillcrest | G7: (876) 152-5006 | H7: Single Payment | I7: 220 | J7: - | K7: - | L7: - | M7: Full | N7: 150 | O7: =SUM(I7:L7) -> 220 | P7: =O7-(O7*$T$5)+N7 -> 348 | Q7: =P7*$T$6 -> 53908.68
A8: 34872 | B8: Avayah | C8: Brown | D8: 36 | E8: Female | F8: 234 Cedar Court, Riverside | G8: (876) 987-5433 | H8: Installment | I8: - | J8: 73.33 | K8: 73.33 | L8: - | M8: Full | N8: 150 | O8: =SUM(I8:L8) -> 146.66 | P8: =O8+(O8*$T$4)+N8 -> 318.659 | Q8: =P8*$T$6 -> 49363.466
A9: 20483 | B9: Eliana | C9: Williams | D9: 18 | E9: Female | F9: 789 Elm Lane, Greenfield | G9: (876) 921-6346 | H9: Single Payment | I9: 220 | J9: - | K9: - | L9: - | M9: Partial | N9: 50 | O9: =SUM(I9:L9) -> 220 | P9: =O9-(O9*$T$5)+N9 -> 248 | Q9: =P9*$T$6 -> 38417.68
A10: 69154 | B10: Jaxton | C10: Jones | D10: 41 | E10: Male | F10: 101 Pine Road, Hilltop | G10: (876) 568-9742 | H10: Single Payment | I10: 220 | J10: - | K10: - | L10: - | M10: Partial | N10: 50 | O10: =SUM(I10:L10) -> 220 | P10: =O10-(O10*$T$5)+N10 -> 248 | Q10: =P10*$T$6 -> 38417.68
A11: 13695 | B11: Natasha | C11: Moore | D11: 22 | E11: Female | F11: 345 Maple Lane, Forest Hills | G11: (876) 999-7682 | H11: Single Payment | I11: 220 | J11: - | K11: - | L11: - | M11: Partial | N11: 50 | O11: =SUM(I11:L11) -> 220 | P11: =O11-(O11*$T$5)+N11 -> 248 | Q11: =P11*$T$6 -> 38417.68
A12: 76391 | B12: Amelia | C12: Anderson | D12: 17 | E12: Female | F12: 911 Elm Street, Parkside | G12: (876) 194-0002 | H12: Single Payment | I12: 220 | J12: - | K12: - | L12: - | M12: Partial | N12: 50 | O12: =SUM(I12:L12) -> 220 | P12: =O12-(O12*$T$5)+N12 -> 248 | Q12: =P12*$T$6 -> 38417.68
A13: 50467 | B13: Kase | C13: Jackson | D13: 26 | E13: Female | F13: 1414 Willow Way, Brookside | G13: (876) 984-1163 | H13: Single Payment | I13: 220 | J13: - | K13: - | L13: - | M13: Partial | N13: 50 | O13: =SUM(I13:L13) -> 220 | P13: =O13-(O13*$T$5)+N13 -> 248 | Q13: =P13*$T$6 -> 38417.68
A14: 91602 | B14: Jenna | C14: Harris | D14: 21 | E14: Female | F14: 1618 Oakwood Drive, Lakeside | G14: (876) 323-5373 | H14: Single Payment | I14: 220 | J14: - | K14: - | L14: - | M14: Partial | N14: 50 | O14: =SUM(I14:L14) -> 220 | P14: =O14-(O14*$T$5)+N14 -> 248 | Q14: =P14*$T$6 -> 38417.68
A15: 29847 | B15: Darian | C15: Thomas | D15: 33 | E15: Male | F15: 1313 Birchwood Avenue, Lakeview | G15: (876) 224-6958 | H15: Installment | I15: - | J15: 73.33 | K15: 73.33 | L15: - | M15: Partial | N15: 50 | O15: =SUM(I15:L15) -> 146.66 | P15: =O15+(O15*$T$4)+N15 -> 218.659 | Q15: =P15*$T$6 -> 33872.466
A16: 57219 | B16: Harry | C16: Johnson | D16: 31 | E16: Male | F16: 456 Oak Avenue, Lakeside | G16: (876) 475-8124 | H16: Installment | I16: - | J16: 73.33 | K16: - | L16: - | M16: Partial | N16: 50 | O16: =SUM(I16:L16) -> 73.33 | P16: =O16+(O16*$T$4)+N16 -> 134.3295 | Q16: =P16*$T$6 -> 20808.983
A17: 40258 | B17: Sawyer | C17: Wilson | D17: 35 | E17: Male | F17: 112 Oakwood Circle, Lakeshore | G17: (876) 756-4212 | H17: Installment | I17: - | J17: 73.33 | K17: - | L17: - | M17: Partial | N17: 50 | O17: =SUM(I17:L17) -> 73.33 | P17: =O17+(O17*$T$4)+N17 -> 134.3295 | Q17: =P17*$T$6 -> 20808.983
A18: 91736 | B18: Madalynn | C18: Mille | D18: 28 | E18: Female | F18: 890 Walnut Avenue, Woodland | G18: (876) 246-8016 | H18: Installment | I18: - | J18: - | K18: - | L18: - | M18: Partial | N18: 50 | O18: =SUM(I18:L18) -> 0 | P18: =O18+(O18*$T$4)+N18 -> 50 | Q18: =P18*$T$6 -> 7745.5
A21: No. of Masqueraders | C21: =COUNT(A4:A19) -> 15 | O21: Total Payment Collected | P21: =SUM(P4:P19) -> 3790.9655 | Q21: =SUM(Q4:Q19) -> 587258.47
A22: Total Costume Payment | C22: =SUM(O4:O19) -> 2639.97
A23: Total Inclusive Fee | C23: =SUMIF(N4:N19,"=150") -> 750
A24: Total Overall Payment | C24: =SUM(P4:P19) -> 3790.9655
A26: EXPENDITURE
A27: Service | B27: Cost Per Person | C27: Flat Rate | D27: Service Interest | E27: Total Cost | F27: Total Cost per Service
A28: Food | B28: 60 | C28: - | D28: 0.2 | E28: =(B28+(B28*D28)) -> 72 | F28: =PRODUCT(E28*$C$21) -> 1080
A29: Drink | B29: 40 | C29: - | D29: 0.2 | E29: =(B29+(B29*D29)) -> 48 | F29: =PRODUCT(E29*$C$21) -> 720
A30: Material | B30: 135 | C30: - | D30: 0.12 | E30: =(B30+(B30*D30)) -> 151.2 | F30: =PRODUCT(E30*$C$21) -> 2268
A31: Labour | B31: 75 | C31: - | D31: 0.08 | E31: =(B31+(B31*D31)) -> 81 | F31: =PRODUCT(E31*$C$21) -> 1215
A32: Bathroom | B32: - | C32: 3000 | D32: - | E32: =C32/5 -> 600 | F32: =PRODUCT(E32,15) -> 9000
A33: Transort | B33: - | C33: 2500 | D33: - | E33: =C33/5 -> 500 | F33: =PRODUCT(E33,15) -> 7500
A34: Music | B34: - | C34: 4000 | D34: - | E34: =C34/5 -> 800 | F34: =PRODUCT(E34,15) -> 12000
A35: Security | B35: - | C35: 1800 | D35: - | E35: =C35/5 -> 360 | F35: =PRODUCT(E35,15) -> 5400
A36: Artiste | B36: - | C36: 5000 | D36: - | E36: =C36/5 -> 1000 | F36: =PRODUCT(E36,15) -> 15000
E38: Total Expenditure | F38: =SUM(F28:F36) -> 54183
A40: Section Name | B40: Total Income | C40: Total Expenditure
A41: Xod-Us | B41: =Q21 -> 587258.47 | C41: =F38 -> 54183
A42: BacchaX | B42: =BacchaX!Q21 -> 494571.24 | C42: =BacchaX!F38 -> 53850
A43: JamCarn X | B43: ='JamCarn X'!Q20 -> 816988.52 | C43: ='JamCarn X'!F37 -> 54912.36
A44: Fant-X | B44: ='Fant-X'!Q18 -> 849396.32 | C44: ='Fant-X'!F35 -> 55754.155
A45: DreamX | B45: =DreamX!Q18 -> 1018096.4 | C45: =DreamX!F35 -> 56727.327

Sheet JamCarn X
A1: Income
A2: ID Number | B2: First name | C2: Last Name | D2: Age | E2: Gender | F2: Address | G2: Phone Number | H2: Costume Payment Option | I2: Full Payment | J2: Installments | M2: Inclusive Fee Option | O2: Total Costume Amount | P2: Total Payment in USD | Q2: Total Payment in JMD
A3: 54261 | B3: Porter | C3: Douglas | D3: 45 | E3: Male | F3: 4 Molynes Rd | G3: (876) 916-4569 | H3: Single Payment | I3: 280 | J3: - | K3: - | L3: - | M3: Full | N3: 150 | O3: =SUM(I3:L3) -> 280 | P3: =O3-(O3*$T$4)+N3 -> 388 | Q3: =P3*$T$5 -> 60105.08 | S3: Interest | T3: 0.1
A4: 52312 | B4: Johnson | C4: Winston | D4: 32 | E4: Male | F4: 16 Seymour Avenue | G4: (876) 926-3790 | H4: Single Payment | I4: 280 | J4: - | K4: - | L4: - | M4: Full | N4: 150 | O4: =SUM(I4:L4) -> 280 | P4: =O4-(O4*$T$4)+N4 -> 388 | Q4: =P4*$T$5 -> 60105.08 | S4: Discount | T4: 0.15
A5: 21523 | B5: Mekaelynn | C5: Moss | D5: 31 | E5: Female | F5: 9 Easton Avenue | G5: (876) 925-3688 | H5: Single Payment | I5: 280 | J5: - | K5: - | L5: - | M5: Partial | N5: 50 | O5: =SUM(I5:L5) -> 280 | P5: =O5-(O5*$T$4)+N5 -> 288 | Q5: =P5*$T$5 -> 44614.08 | S5: JMD Equivalent | T5: 154.91
A6: 23565 | B6: Xander | C6: Reeves | D6: 23 | E6: Male | F6: 85 Hagley Park Rd | G6: (876) 961-3971 | H6: Installment | I6: - | J6: 93.33 | K6: - | L6: - | M6: Full | N6: 150 | O6: =SUM(I6:L6) -> 93.33 | P6: =O6+(O6*$T$3)+N6 -> 252.663 | Q6: =P6*$T$5 -> 39140.025
A7: 23215 | B7: Shawn | C7: Stevenson | D7: 40 | E7: Male | F7: 30 Dunrobin Avenue | G7: (876) 754-3678 | H7: Installment | I7: - | J7: 93.33 | K7: 93.33 | L7: 93.33 | M7: Full | N7: 150 | O7: =SUM(I7:L7) -> 279.99 | P7: =O7+(O7*$T$3)+N7 -> 457.989 | Q7: =P7*$T$5 -> 70947.076
A8: 21357 | B8: Tae | C8: Bryan | D8: 42 | E8: Male | F8: 72 Hope Rd | G8: (876) 926-3221 | H8: Single Payment | I8: 280 | J8: - | K8: - | L8: - | M8: Partial | N8: 50 | O8: =SUM(I8:L8) -> 280 | P8: =O8-(O8*$T$4)+N8 -> 288 | Q8: =P8*$T$5 -> 44614.08
A9: 98654 | B9: Anabelle | C9: Huang | D9: 14 | E9: Female | F9: 53 Knutsford Blvd | G9: (876) 927-8911 | H9: Single Payment | I9: 280 | J9: - | K9: - | L9: - | M9: Partial | N9: 50 | O9: =SUM(I9:L9) -> 280 | P9: =O9-(O9*$T$4)+N9 -> 288 | Q9: =P9*$T$5 -> 44614.08
A10: 45216 | B10: Jenny | C10: Cortez | D10: 32 | E10: Female | F10: 87a Orange | G10: (876) 934-9187 | H10: Installment | I10: - | J10: 93.33 | K10: - | L10: - | M10: Full | N10: 150 | O10: =SUM(I10:L10) -> 93.33 | P10: =O10+(O10*$T$3)+N10 -> 252.663 | Q10: =P10*$T$5 -> 39140.025
A11: 21354 | B11: Becca | C11: Welch | D11: 35 | E11: Female | F11: 12 Ruthven Rd | G11: (876) 964-8396 | H11: Installment | I11: - | J11: 93.33 | K11: 93.33 | L11: - | M11: Full | N11: 150 | O11: =SUM(I11:L11) -> 186.66 | P11: =O11+(O11*$T$3)+N11 -> 355.326 | Q11: =P11*$T$5 -> 55043.551
A12: 84521 | B12: Eli | C12: Mendez | D12: 23 | E12: Male | F12: Wentworth | G12: (876) 479-3196 | H12: Installment | I12: - | J12: 93.33 | K12: - | L12: - | M12: Partial | N12: 50 | O12: =SUM(I12:L12) -> 93.33 | P12: =O12+(O12*$T$3)+N12 -> 152.663 | Q12: =P12*$T$5 -> 23649.025
A13: 26589 | B13: Alia | C13: Tang | D13: 28 | E13: Female | F13: 123 Constant Spring Rd | G13: (876) 914-1656 | H13: Installment | I13: - | J13: 93.33 | K13: 93.33 | L13: 93.33 | M13: Full | N13: 150 | O13: =SUM(I13:L13) -> 279.99 | P13: =O13+(O13*$T$3)+N13 -> 457.989 | Q13: =P13*$T$5 -> 70947.076
A14: 26897 | B14: Brina | C14: Cochran | D14: 37 | E14: Female | F14: 14 Half Retirement Rd | G14: (876) 934-0826 | H14: Single Payment | I14: 280 | J14: - | K14: - | L14: - | M14: Full | N14: 150 | O14: =SUM(I14:L14) -> 280 | P14: =O14-(O14*$T$4)+N14 -> 388 | Q14: =P14*$T$5 -> 60105.08
A15: 32326 | B15: Bryann | C15: Castro | D15: 39 | E15: Male | F15: 21 Red Hills Rd | G15: (876) 931-2456 | H15: Single Payment | I15: 280 | J15: - | K15: - | L15: - | M15: Full | N15: 150 | O15: =SUM(I15:L15) -> 280 | P15: =O15-(O15*$T$4)+N15 -> 388 | Q15: =P15*$T$5 -> 60105.08
A16: 21532 | B16: Lucas | C16: Stark | D16: 16 | E16: Male | F16: 24 Riverton Blvd | G16: (876) 913-8666 | H16: Single Payment | I16: 280 | J16: - | K16: - | L16: - | M16: Full | N16: 150 | O16: =SUM(I16:L16) -> 280 | P16: =O16-(O16*$T$4)+N16 -> 388 | Q16: =P16*$T$5 -> 60105.08
A17: 65236 | B17: Marlee | C17: Ben | D17: 27 | E17: Female | F17: 33 Friendship Drive | G17: (876) 472-695 | H17: Installment | I17: - | J17: 93.33 | K17: - | L17: - | M17: Partial | N17: 50 | O17: =SUM(I17:L17) -> 93.33 | P17: =O17+(O17*$T$3)+N17 -> 152.663 | Q17: =P17*$T$5 -> 23649.025
A18: 21234 | B18: Jessie | C18: Fox | D18: 36 | E18: Female | F18: 10 Trafalgar Rd | G18: (876) 934-3049 | H18: Single Payment | I18: 280 | J18: - | K18: - | L18: - | M18: Full | N18: 150 | O18: =SUM(I18:L18) -> 280 | P18: =O18-(O18*$T$4)+N18 -> 388 | Q18: =P18*$T$5 -> 60105.08
A20: No. of Masqueraders | C20: =COUNT(A2:A18) -> 16 | O20: Total Payment Collected | P20: =SUM(P3:P18) -> 5273.956 | Q20: =SUM(Q3:Q18) -> 816988.52
A21: Total Costume Payment | C21: =SUM(O3:O18) -> 3639.96
A22: Total Inclusive Fee | C22: =SUMIF(N3:N18,"=150") -> 1650
A23: Total Overall Payment | C23: =SUM(P3:P18) -> 5273.956
A25: EXPENDITURE
A26: Service | B26: Cost Per Person | C26: Flat Rate | D26: Service Interest | E26: Total Cost | F26: Total Cost per Service
A27: Food | B27: 60 | C27: - | D27: 0.2 | E27: ='Xod-Us'!E28*D27+'Xod-Us'!E28 -> 86.4 | F27: =PRODUCT(E27,15) -> 1296
A28: Drink | B28: 40 | C28: - | D28: 0.2 | E28: ='Xod-Us'!E29*D28+'Xod-Us'!E29 -> 57.6 | F28: =PRODUCT(E28,15) -> 864
A29: Material | B29: 135 | C29: - | D29: 0.12 | E29: ='Xod-Us'!E30*D29+'Xod-Us'!E30 -> 169.344 | F29: =PRODUCT(E29,15) -> 2540.16
A30: Labour | B30: 75 | C30: - | D30: 0.08 | E30: ='Xod-Us'!E31*D30+'Xod-Us'!E31 -> 87.48 | F30: =PRODUCT(E30,15) -> 1312.2
A31: Bathroom | B31: - | C31: 3000 | D31: - | E31: =C31/5 -> 600 | F31: =PRODUCT(E31,15) -> 9000
A32: Transort | B32: - | C32: 2500 | D32: - | E32: =C32/5 -> 500 | F32: =PRODUCT(E32,15) -> 7500
A33: Music | B33: - | C33: 4000 | D33: - | E33: =C33/5 -> 800 | F33: =PRODUCT(E33,15) -> 12000
A34: Security | B34: - | C34: 1800 | D34: - | E34: =C34/5 -> 360 | F34: =PRODUCT(E34,15) -> 5400
A35: Artiste | B35: - | C35: 5000 | D35: - | E35: =C35/5 -> 1000 | F35: =PRODUCT(E35,15) -> 15000
E37: Total Expenditure | F37: =SUM(F27:F35) -> 54912.36
A39: Section Name | B39: Total Income | C39: Total Expenditure
A40: JamCarn X | B40: =Q20 -> 816988.52 | C40: =F37 -> 54912.36
A41: BacchaX | B41: =BacchaX!Q21 -> 494571.24 | C41: =BacchaX!F38 -> 53850
A42: Xod-Us | B42: ='Xod-Us'!Q21 -> 587258.47 | C42: ='Xod-Us'!F38 -> 54183
A43: Fant-X | B43: ='Fant-X'!Q18 -> 849396.32 | C43: ='Fant-X'!F35 -> 55754.155
A44: DreamX | B44: =DreamX!Q18 -> 1018096.4 | C44: =DreamX!F35 -> 56727.327

Sheet Fant-X
A1: Income
A2: ID Number | B2: First name | C2: Last Name | D2: Age | E2: Gender | F2: Address | G2: Phone Number | H2: Costume Payment Option | I2: Full Payment | J2: Installments | M2: Inclusive Fee Option | O2: Total Costume Amount | P2: Total Payment in USD | Q2: Total Payment in JMD
A3: 47933 | B3: Brix | C3: Anderson | D3: 32 | E3: Female | F3: 25 East Gueen | G3: (876) 922-6981 | H3: Single Payment | I3: 350 | J3: - | K3: - | L3: - | M3: Partial | N3: 50 | O3: =SUM(I3:L3) -> 350 | P3: =O3-(O3*$T$4)+N3 -> 347.5 | Q3: =P3*$T$5 -> 53831.225 | S3: Interest | T3: 0.1
A4: 32456 | B4: Ava | C4: Garcia | D4: 49 | E4: Female | F4: 2 Molynes Rd | G4: (876) 923-7282 | H4: Single Payment | I4: 350 | J4: - | K4: - | L4: - | M4: Partial | N4: 50 | O4: =SUM(I4:L4) -> 350 | P4: =O4-(O4*$T$4)+N4 -> 347.5 | Q4: =P4*$T$5 -> 53831.225 | S4: Discount | T4: 0.15
A5: 42357 | B5: Clark | C5: Martinez | D5: 43 | E5: Female | F5: 3 Duke | G5: (876) 922-6156 | H5: Installment | I5: - | J5: 116.7 | K5: 116.7 | L5: 116.7 | M5: Partial | N5: 50 | O5: =SUM(I5:L5) -> 350.1 | P5: =O5+(O5*$T$3)+N5 -> 435.11 | Q5: =P5*$T$5 -> 67402.89 | S5: JMD Equivalent | T5: 154.91
A6: 20445 | B6: Lee | C6: Scott | D6: 25 | E6: Male | F6: 53 Gilmour Dr | G6: (876) 925-4575 | H6: Single Payment | I6: 350 | J6: - | K6: - | L6: - | M6: Full | N6: 150 | O6: =SUM(I6:L6) -> 350 | P6: =O6-(O6*$T$4)+N6 -> 447.5 | Q6: =P6*$T$5 -> 69322.225
A7: 73924 | B7: Charleigh | C7: Johnson | D7: 31 | E7: Female | F7: 63 Mark Lane | G7: (876) 967-0910 | H7: Installment | I7: - | J7: 116.7 | K7: 116.7 | L7: - | M7: Partial | N7: 50 | O7: =SUM(I7:L7) -> 233.4 | P7: =O7+(O7*$T$3)+N7 -> 306.74 | Q7: =P7*$T$5 -> 47517.093
A8: 92123 | B8: Seven | C8: Williams | D8: 24 | E8: Male | F8: 327a Spain 1 | G8: (876) 901-5214 | H8: Single Payment | I8: 350 | J8: - | K8: - | L8: - | M8: Full | N8: 150 | O8: =SUM(I8:L8) -> 350 | P8: =O8-(O8*$T$4)+N8 -> 447.5 | Q8: =P8*$T$5 -> 69322.225
A9: 57136 | B9: Joy | C9: Lee | D9: 33 | E9: Female | F9: 8 Haughton Ave | G9: (876) 903-1033 | H9: Installment | I9: - | J9: 116.7 | K9: - | L9: - | M9: Full | N9: 150 | O9: =SUM(I9:L9) -> 116.7 | P9: =O9+(O9*$T$3)+N9 -> 278.37 | Q9: =P9*$T$5 -> 43122.297
A10: 31274 | B10: Royce | C10: Taylor | D10: 53 | E10: Male | F10: 39 Caracas Ave | G10: (876) 921-6894 | H10: Installment | I10: - | J10: 116.7 | K10: 116.7 | L10: - | M10: Partial | N10: 50 | O10: =SUM(I10:L10) -> 233.4 | P10: =O10+(O10*$T$3)+N10 -> 306.74 | Q10: =P10*$T$5 -> 47517.093
A11: 20212 | B11: Khalid | C11: Patel | D11: 23 | E11: Male | F11: 7 Lady Musgrave Rd | G11: (876) 924-5626 | H11: Installment | I11: - | J11: 116.7 | K11: 116.7 | L11: 116.7 | M11: Partial | N11: 50 | O11: =SUM(I11:L11) -> 350.1 | P11: =O11+(O11*$T$3)+N11 -> 435.11 | Q11: =P11*$T$5 -> 67402.89
A12: 14392 | B12: Quenton | C12: Rodriguez | D12: 21 | E12: Male | F12: Upr Elletson Rd | G12: (876) 924-1024 | H12: Single Payment | I12: 350 | J12: - | K12: - | L12: - | M12: Full | N12: 150 | O12: =SUM(I12:L12) -> 350 | P12: =O12+(O12*$T$3)+N12 -> 535 | Q12: =P12*$T$5 -> 82876.85
A13: 30791 | B13: Axl | C13: Martinez | D13: 40 | E13: Male | F13: Gordon Town | G13: (876) 701-1866 | H13: Installment | I13: - | J13: 116.7 | K13: 116.7 | L13: - | M13: Full | N13: 150 | O13: =SUM(I13:L13) -> 233.4 | P13: =O13+(O13*$T$3)+N13 -> 406.74 | Q13: =P13*$T$5 -> 63008.093
A14: 89532 | B14: Myla | C14: Clark | D14: 39 | E14: Female | F14: 51 Gilmour Drive | G14: (876) 922-5291 | H14: Installment | I14: - | J14: 116.7 | K14: 116.7 | L14: - | M14: Partial | N14: 50 | O14: =SUM(I14:L14) -> 233.4 | P14: =O14+(O14*$T$3)+N14 -> 306.74 | Q14: =P14*$T$5 -> 47517.093
A15: 11469 | B15: Emillio | C15: Smith | D15: 17 | E15: Male | F15: 71 Molynes Rd | G15: (876) 754-8099 | H15: Installment | I15: - | J15: 116.7 | K15: 116.7 | L15: 116.7 | M15: Full | N15: 150 | O15: =SUM(I15:L15) -> 350.1 | P15: =O15+(O15*$T$3)+N15 -> 535.11 | Q15: =P15*$T$5 -> 82893.89
A16: 39745 | B16: Arabella | C16: Brown | D16: 34 | E16: Female | F16: Twickenham Pk | G16: (876) 982-3092 | H16: Single Payment | I16: 350 | J16: - | K16: - | L16: - | M16: Partial | N16: 50 | O16: =SUM(I16:L16) -> 350 | P16: =O16-(O16*$T$4)+N16 -> 347.5 | Q16: =P16*$T$5 -> 53831.225
A18: No. of Masqueraders | C18: =COUNT(A2:A16) -> 14 | O18: Total Payment Collected | P18: =SUM(P3:P16) -> 5483.16 | Q18: =SUM(Q3:Q16) -> 849396.32
A19: Total Costume Payment | C19: =SUM(O3:O16) -> 4200.6
A20: Total Inclusive Fee | C20: =SUMIF(N3:N16,"=150") -> 900
A21: Total Overall Payment | C21: =SUM(P3:P16) -> 5483.16
A23: EXPENDITURE
A24: Service | B24: Cost Per Person | C24: Flat Rate | D24: Service Interest | E24: Total Cost | F24: Total Cost per Service
A25: Food | B25: 60 | C25: - | D25: 0.2 | E25: ='JamCarn X'!E27*D25+'JamCarn X'!E27 -> 103.68 | F25: =PRODUCT(E25,15) -> 1555.2
A26: Drink | B26: 40 | C26: - | D26: 0.2 | E26: ='JamCarn X'!E28*D26+'JamCarn X'!E28 -> 69.12 | F26: =PRODUCT(E26,15) -> 1036.8
A27: Material | B27: 135 | C27: - | D27: 0.12 | E27: ='JamCarn X'!E29*D27+'JamCarn X'!E29 -> 189.66528 | F27: =PRODUCT(E27,15) -> 2844.9792
A28: Labour | B28: 75 | C28: - | D28: 0.08 | E28: ='JamCarn X'!E30*D28+'JamCarn X'!E30 -> 94.4784 | F28: =PRODUCT(E28,15) -> 1417.176
A29: Bathroom | B29: - | C29: 3000 | D29: - | E29: =C29/5 -> 600 | F29: =PRODUCT(E29,15) -> 9000
A30: Transort | B30: - | C30: 2500 | D30: - | E30: =C30/5 -> 500 | F30: =PRODUCT(E30,15) -> 7500
A31: Music | B31: - | C31: 4000 | D31: - | E31: =C31/5 -> 800 | F31: =PRODUCT(E31,15) -> 12000
A32: Security | B32: - | C32: 1800 | D32: - | E32: =C32/5 -> 360 | F32: =PRODUCT(E32,15) -> 5400
A33: Artiste | B33: - | C33: 5000 | D33: - | E33: =C33/5 -> 1000 | F33: =PRODUCT(E33,15) -> 15000
E35: Total Expenditure | F35: =SUM(F25:F33) -> 55754.155
A37: Section Name | B37: Total Income | C37: Total Expenditure
A38: Fant-X | B38: =Q18 -> 849396.32 | C38: =F35 -> 55754.155
A39: BacchaX | B39: =BacchaX!Q21 -> 494571.24 | C39: =BacchaX!F38 -> 53850
A40: Xod-Us | B40: ='Xod-Us'!Q21 -> 587258.47 | C40: ='Xod-Us'!F38 -> 54183
A41: JamCarn X | B41: ='JamCarn X'!Q20 -> 816988.52 | C41: ='JamCarn X'!F37 -> 54912.36
A42: DreamX | B42: =DreamX!Q18 -> 1018096.4 | C42: =DreamX!F35 -> 56727.327

Sheet DreamX
A1: Income
A2: ID Number | B2: First name | C2: Last Name | D2: Age | E2: Gender | F2: Address | G2: Phone Number | H2: Costume Payment Option | I2: Full Payment | J2: Installments | M2: Inclusive Fee Option | O2: Total Costume Amount | P2: Total Payment in USD | Q2: Total Payment in JMD
A3: 23569 | B3: Ryann | C3: White | D3: 38 | E3: Male | F3: 4 Dunrobin Ave | G3: (876) 925-4741 | H3: Single Payment | I3: 425 | J3: - | K3: - | L3: - | M3: Partial | N3: 50 | O3: =SUM(I3:L3) -> 425 | P3: =O3-(O3*$T$4)+N3 -> 411.25 | Q3: =P3*$T$5 -> 63706.737 | S3: Interest | T3: 0.1
A4: 81527 | B4: Izabella | C4: simmonds | D4: 32 | E4: Female | F4: White Marl | G4: (876) 984-2749 | H4: Single Payment | I4: 425 | J4: - | K4: - | L4: - | M4: Full | N4: 150 | O4: =SUM(I4:L4) -> 425 | P4: =O4-(O4*$T$4)+N4 -> 511.25 | Q4: =P4*$T$5 -> 79197.738 | S4: Discount | T4: 0.15
A5: 98744 | B5: Tobias | C5: Nguyen | D5: 44 | E5: Male | F5: 4 Goodwood Terr | G5: (876) 135-6922 | H5: Single Payment | I5: 425 | J5: - | K5: - | L5: - | M5: Partial | N5: 50 | O5: =SUM(I5:L5) -> 425 | P5: =O5-(O5*$T$4)+N5 -> 411.25 | Q5: =P5*$T$5 -> 63706.737 | S5: JMD Equivalent | T5: 154.91
A6: 68402 | B6: Emory | C6: Baker | D6: 39 | E6: Male | F6: Church rd | G6: (876) 929-3073 | H6: Installment | I6: - | J6: 141.7 | K6: - | L6: - | M6: Partial | N6: 50 | O6: =SUM(I6:L6) -> 141.7 | P6: =O6+(O6*$T$3)+N6 -> 205.87 | Q6: =P6*$T$5 -> 31891.322
A7: 45305 | B7: Sloan | C7: Robinson | D7: 33 | E7: Female | F7: 22a Union St | G7: (876) 979-0064 | H7: Installment | I7: - | J7: 141.7 | K7: 141.7 | L7: 141.7 | M7: Full | N7: 150 | O7: =SUM(I7:L7) -> 425.1 | P7: =O7+(O7*$T$3)+N7 -> 617.61 | Q7: =P7*$T$5 -> 95673.965
A8: 74128 | B8: Brooklyn | C8: Thompson | D8: 28 | E8: Female | F8: 1/2 Munroe Rd | G8: (876) 927-7362 | H8: Single Payment | I8: 425 | J8: - | K8: - | L8: - | M8: Full | N8: 150 | O8: =SUM(I8:L8) -> 425 | P8: =O8-(O8*$T$4)+N8 -> 511.25 | Q8: =P8*$T$5 -> 79197.738
A9: 36216 | B9: Carla | C9: Lee | D9: 25 | E9: Female | F9: 6 Caledonia Ave | G9: (876) 929-6663 | H9: Installment | I9: - | J9: 141.7 | K9: 141.7 | L9: - | M9: Full | N9: 150 | O9: =SUM(I9:L9) -> 283.4 | P9: =O7+(O7*$T$3)+N7 -> 617.61 | Q9: =P9*$T$5 -> 95673.965
A10: 87391 | B10: Marcus | C10: Bennett | D10: 31 | E10: Female | F10: 58 HWT Rd | G10: (876) 929-8493 | H10: Single Payment | I10: 425 | J10: - | K10: - | L10: - | M10: Partial | N10: 50 | O10: =SUM(I10:L10) -> 425 | P10: =O10-(O10*$T$4)+N10 -> 411.25 | Q10: =P10*$T$5 -> 63706.737
A11: 87640 | B11: Frankie | C11: Stewart | D11: 47 | E11: Male | F11: 14 Ballater Ave | G11: (876) 968-4932 | H11: Single Payment | I11: 425 | J11: - | K11: - | L11: - | M11: Full | N11: 150 | O11: =SUM(I11:L11) -> 425 | P11: =O11-(O11*$T$4)+N11 -> 511.25 | Q11: =P11*$T$5 -> 79197.738
A12: 62902 | B12: Keyla | C12: Parker | D12: 22 | E12: Female | F12: 136a Red Hills Rd | G12: (876) 931-8320 | H12: Installment | I12: - | J12: 141.7 | K12: 141.7 | L12: 141.7 | M12: Full | N12: 150 | O12: =SUM(I12:L12) -> 425.1 | P12: =O12+(O12*$T$3)+N12 -> 617.61 | Q12: =P12*$T$5 -> 95673.965
A13: 51301 | B13: Martha | C13: Hill | D13: 23 | E13: Female | F13: 3 Beechwood Ave | G13: (876) 929-1482 | H13: Single Payment | I13: 425 | J13: - | K13: - | L13: - | M13: Partial | N13: 50 | O13: =SUM(I13:L13) -> 425 | P13: =O13-(O13*$T$4)+N13 -> 411.25 | Q13: =P13*$T$5 -> 63706.737
A14: 29872 | B14: Ruby | C14: Owens | D14: 19 | E14: Female | F14: 59 Lyndhurst Rd | G14: (876) 985-2012 | H14: Single Payment | I14: 425 | J14: - | K14: - | L14: - | M14: Full | N14: 150 | O14: =SUM(I14:L14) -> 425 | P14: =O14-(O14*$T$4)+N14 -> 511.25 | Q14: =P14*$T$5 -> 79197.738
A15: 14685 | B15: Samuel | C15: leach | D15: 30 | E15: Male | F15: 1 Kent Ave | G15: (876) 952-4373 | H15: Installment | I15: - | J15: 141.7 | K15: 141.7 | L15: 141.7 | M15: Partial | N15: 50 | O15: =SUM(I15:L15) -> 425.1 | P15: =O15+(O15*$T$3)+N15 -> 517.61 | Q15: =P15*$T$5 -> 80182.965
A16: 30959 | B16: Zoe | C16: Mitch | D16: 21 | E16: Female | F16: Spur Tree | G16: (876) 962-2211 | H16: Installment | I16: - | J16: 141.7 | K16: - | L16: - | M16: Full | N16: 150 | O16: =SUM(I16:L16) -> 141.7 | P16: =O16+(O16*$T$3)+N16 -> 305.87 | Q16: =P16*$T$5 -> 47382.322
A18: No. of Masqueraders | C18: =COUNT(A2:A16) -> 14 | O18: Total Payment Collected | P18: =SUM(P3:P16) -> 6572.18 | Q18: =SUM(Q3:Q16) -> 1018096.4
A19: Total Costume Payment | C19: =SUM(O3:O16) -> 5242.1
A20: Total Inclusive Fee | C20: =SUMIF(N3:N16,"=150") -> 1200
A21: Total Overall Payment | C21: =SUM(P3:P16) -> 6572.18
A23: EXPENDITURE
A24: Service | B24: Cost Per Person | C24: Flat Rate | D24: Service Interest | E24: Total Cost | F24: Total Cost per Service
A25: Food | B25: 60 | C25: - | D25: 0.2 | E25: ='Fant-X'!E25*D25+'Fant-X'!E25 -> 124.416 | F25: =PRODUCT(E25,15) -> 1866.24
A26: Drink | B26: 40 | C26: - | D26: 0.2 | E26: ='Fant-X'!E26*D26+'Fant-X'!E26 -> 82.944 | F26: =PRODUCT(E26,15) -> 1244.16
A27: Material | B27: 135 | C27: - | D27: 0.12 | E27: ='Fant-X'!E27*D27+'Fant-X'!E27 -> 212.42511 | F27: =PRODUCT(E27,15) -> 3186.3767
A28: Labour | B28: 75 | C28: - | D28: 0.08 | E28: ='Fant-X'!E28*D28+'Fant-X'!E28 -> 102.03667 | F28: =PRODUCT(E28,15) -> 1530.5501
A29: Bathroom | B29: - | C29: 3000 | D29: - | E29: =C29/5 -> 600 | F29: =PRODUCT(E29,15) -> 9000
A30: Transort | B30: - | C30: 2500 | D30: - | E30: =C30/5 -> 500 | F30: =PRODUCT(E30,15) -> 7500
A31: Music | B31: - | C31: 4000 | D31: - | E31: =C31/5 -> 800 | F31: =PRODUCT(E31,15) -> 12000
A32: Security | B32: - | C32: 1800 | D32: - | E32: =C32/5 -> 360 | F32: =PRODUCT(E32,15) -> 5400
A33: Artiste | B33: - | C33: 5000 | D33: - | E33: =C33/5 -> 1000 | F33: =PRODUCT(E33,15) -> 15000
E35: Total Expenditure | F35: =SUM(F25:F33) -> 56727.327
A37: Section Name | B37: Total Income | C37: Total Expenditure
A38: DreamX | B38: =Q18 -> 1018096.4 | C38: =F35 -> 56727.327
A39: BacchaX | B39: =BacchaX!Q21 -> 494571.24 | C39: =BacchaX!F38 -> 53850
A40: Xod-Us | B40: ='Xod-Us'!Q21 -> 587258.47 | C40: ='Xod-Us'!F38 -> 54183
A41: JamCarn X | B41: ='JamCarn X'!Q20 -> 816988.52 | C41: ='JamCarn X'!F37 -> 54912.36
A42: Fant - X | B42: ='Fant-X'!Q18 -> 849396.32 | C42: ='Fant-X'!F35 -> 55754.155

Sheet Pivot Table
A3: Row Labels | B3: Sum of Total Income | C3: Sum of Total Expenditure
A4: BacchaX | B4: 494571.24 | C4: 53850
A5: DreamX | B5: 1018096.4 | C5: 56727.327
A6: Fant - X | B6: 849396.32 | C6: 55754.155
A7: JamCarn X | B7: 816988.52 | C7: 54912.36
A8: Xod-Us | B8: 587258.47 | C8: 54183
A9: Grand Total | B9: 3766311 | C9: 275426.84
