Workbook

Sheet BacchahX
A1: Income
A2: ID Number | B2: First name | C2: Last Name | D2: Age | E2: Gender | F2: Address | G2: Phone Number | H2: Costume Payment Option | I2: Full Payment | J2: Installments | M2: Inclusive Fee Option | O2: Total Costume Amount | P2: Total Payment in USD | Q2: Total Payment in JMD
A3: 20006 | B3: Emily | C3: Johnson | D3: 28 | E3: Female | F3: 231 Maple Street | G3: (876) 253-2857 | H3: Installment | I3: - | J3: 53.33 | K3: 53.33 | L3: 53.33 | M3: Full | N3: 150 | O3: =SUM(I3:L3) -> 159.99 | P3: =O3+(O3*$T$3)+N3 -> 333.9885 | Q3: =P3*$T$5 -> 51738.159 | S3: Interest | T3: 0.15
A4: 20007 | B4: Micheal | C4: Smith | D4: 35 | E4: Male | F4: 476 Oak Avenue | G4: (876) 756-485 | H4: Installment | I4: - | J4: 53.33 | K4: - | L4: - | M4: Full | N4: 150 | O4: =SUM(I4:L4) -> 53.33 | P4: =O4+(O4*$T$3)+N4 -> 211.3295 | Q4: =P4*$T$5 -> 32737.053 | S4: Discount | T4: 0.1
A5: 20001 | B5: Sophia | C5: Wiliams | D5: 22 | E5: Female | F5: 879 Pine Road | G5: (876)738-4989 | H5: Single Payment | I5: 160 | J5: - | K5: - | L5: - | M5: Full | N5: 150 | O5: =SUM(I5:L5) -> 160 | P5: =O5-(O5*$T$4)+N5 -> 294 | Q5: =P5*$T$5 -> 45543.54 | S5: JMD Equivalent | T5: 154.91
A6: 20002 | B6: Benjamin | C6: Brown | D6: 40 | E6: Male | F6: 101 Elm Lane | G6: (876) 948-3947 | H6: Single Payment | I6: 160 | J6: - | K6: - | L6: - | M6: Partial | N6: 50 | O6: =SUM(I6:L6) -> 160 | P6: =O6-(O6*$T$4)+N6 -> 194 | Q6: =P6*$T$5 -> 30052.54
A7: 20003 | B7: Olivia | C7: Jones | D7: 26 | E7: Female | F7: 647 Cedar Street | G7: (876) 378-9387 | H7: Single Playment | I7: 160 | J7: - | K7: - | L7: - | M7: Partial | N7: 50 | O7: =SUM(I7:L7) -> 160 | P7: =O7-(O7*$T$4)+N7 -> 194 | Q7: =P7*$T$5 -> 30052.54
A8: 20008 | B8: Jacob | C8: Davis | D8: 33 | E8: Male | F8: 756 Birch Boluevard | G8: (876) 378-9388 | H8: Installment | I8: - | J8: 53.33 | K8: - | L8: - | M8: Full | N8: 150 | O8: =SUM(I8:L8) -> 53.33 | P8: =O8+(O8*$T$3)+N8 -> 211.3295 | Q8: =P8*$T$5 -> 32737.053
A9: 20004 | B9: Isabella | C9: Taylor | D9: 29 | E9: Female | F9: 890 Willow Drive | G9: (876) 368-9389 | H9: Single Payment | I9: 160 | J9: - | K9: - | L9: - | M9: Full | N9: 150 | O9: =SUM(I9:L9) -> 160 | P9: =O9-(O9*$T$4)+N9 -> 294 | Q9: =P9*$T$5 -> 45543.54
A10: 20005 | B10: Matthew | C10: Martinez | D10: 37 | E10: Male | F10: 121 Magnolia Court | G10: (876) 336-9390 | H10: Installment | I10: - | J10: - | K10: - | L10: - | M10: Partial | N10: 50 | O10: =SUM(I10:L10) -> 0 | P10: =O10+(O10*$T$3)+N10 -> 50 | Q10: =P10*$T$5 -> 7745.5
A11: 20009 | B11: Emma | C11: Anderson | D11: 24 | E11: Female | F11: 342 Cherry Lane | G11: (876) 338-9391 | H11: Installment | I11: - | J11: 53.33 | K11: 53.33 | L11: 53.33 | M11: Full | N11: 150 | O11: =SUM(I11:L11) -> 159.99 | P11: =O11+(O11*$T$3)+N11 -> 333.9885 | Q11: =P11*$T$5 -> 51738.159
A12: 20010 | B12: Ethan | C12: Garcia | D12: 31 | E12: Male | F12: 435 Spruce Avenue | G12: (876) 434-2345 | H12: Installment | I12: - | J12: 53.33 | K12: - | L12: - | M12: Partial | N12: 50 | O12: =SUM(I12:L12) -> 53.33 | P12: =O12+(O12*$T$3)+N12 -> 111.3295 | Q12: =P12*$T$5 -> 17246.053
A13: 20011 | B13: Ava | C13: Rodriquez | D13: 27 | E13: Female | F13: 116 Walnut Way | G13: (876) 284-9393 | H13: Installment | I13: - | J13: - | K13: - | L13: - | M13: Partial | N13: 50 | O13: =SUM(I13:L13) -> 0 | P13: =O13+(O13*$T$3)+N13 -> 50 | Q13: =P13*$T$5 -> 7745.5
A14: 20012 | B14: William | C14: Wilson | D14: 36 | E14: Male | F14: 878 Ash Street | G14: (876) 503-9394 | H14: Single Payment | I14: 160 | J14: - | K14: - | L14: - | M14: Full | N14: 150 | O14: =SUM(I14:L14) -> 160 | P14: =O14-(O14*$T$4)+N14 -> 294 | Q14: =P14*$T$5 -> 45543.54
A15: 20013 | B15: Mia | C15: Hernandez | D15: 23 | E15: Female | F15: 748 Birch Lane | G15: (876) 332-9395 | H15: Single Payment | I15: 160 | J15: - | K15: - | L15: - | M15: Full | N15: 150 | O15: =SUM(I15:L15) -> 160 | P15: =O15-(O15*$T$4)+N15 -> 294 | Q15: =P15*$T$5 -> 45543.54
A16: 20014 | B16: Alexander | C16: Lopez | D16: 30 | E16: Male | F16: 676 Sycamore Street | G16: (876) 388-9396 | H16: Single Payment | I16: 160 | J16: - | K16: - | L16: - | M16: Full | N16: 150 | O16: =SUM(I16:L16) -> 160 | P16: =O16-(O16*$T$4)+N16 -> 294 | Q16: =P16*$T$5 -> 45543.54
A17: 20015 | B17: Charlotte | C17: Gonzalez | D17: 25 | E17: Female | F17: 263 Maple Avenue | G17: (876) 238-9397 | H17: Installment | I17: - | J17: 53.33 | K17: 53.33 | L17: - | M17: Partial | N17: 50 | O17: =SUM(I17:L17) -> 106.66 | P17: =O17+(O17*$T$3)+N17 -> 172.659 | Q17: =P17*$T$5 -> 26746.606
A19: No. of Masqueraders | C19: =COUNT(A3:A17) -> 15 | O19: Total Payment Collected | P19: =SUM(P3:P17) -> 3332.6245 | Q19: =SUM(Q3:Q17) -> 516256.86
A20: Total Costume Payment | C20: =SUM(O3:O17) -> 1706.63
A21: Total Inclusive Fee | C21: =SUMIF(N3:N17,"=150") -> 1350
A22: Total Overall Payment | C22: =SUM(P3:P17) -> 3332.6245
A24: EXPENDITURE
A25: Service | B25: Cost Per Person | C25: Flat Rate | D25: Service Interest | E25: Total Cost | F25: Total Cost per Service
A26: Food | B26: 60 | C26: - | D26: 0.15 | E26: =B26 -> 60 | F26: =PRODUCT(E26*$C$19) -> 900
A27: Drink | B27: 40 | C27: - | D27: 0.15 | E27: =B27 -> 40 | F27: =PRODUCT(E27*$C$19) -> 600
A28: Material | B28: 150 | C28: - | D28: 0.12 | E28: =B28 -> 150 | F28: =PRODUCT(E28*$C$19) -> 2250
A29: Labour | B29: 75 | C29: - | D29: 0.08 | E29: =B29 -> 75 | F29: =PRODUCT(E29*$C$19) -> 1125
A30: Bathroom | B30: - | C30: 3000 | D30: - | E30: =C30/5 -> 600 | F30: =PRODUCT(E30,15) -> 9000
A31: Transort | B31: - | C31: 2500 | D31: - | E31: =C31/5 -> 500 | F31: =PRODUCT(E31,15) -> 7500
A32: Music | B32: - | C32: 4000 | D32: - | E32: =C32/5 -> 800 | F32: =PRODUCT(E32,15) -> 12000
A33: Security | B33: - | C33: 1800 | D33: - | E33: =C33/5 -> 360 | F33: =PRODUCT(E33,15) -> 5400
A34: Artiste | B34: - | C34: 5000 | D34: - | E34: =C34/5 -> 1000 | F34: =PRODUCT(E34,15) -> 15000
E36: Total Expenditure | F36: =SUM(F26:F34) -> 53775

Sheet Xod-Us
A1: Income
A2: ID Number | B2: First name | C2: Last Name | D2: Age | E2: Gender | F2: Address | G2: Phone Number | H2: Costume Payment Option | I2: Full Payment | J2: Installments | M2: Inclusive Fee Option | O2: Total Costume Amount | P2: Total Payment in USD | Q2: Total Payment in JMD
A3: 30001 | B3: Emma | C3: Smith | D3: 25 | E3: Female | F3: 123 Maple Street, Springfield | G3: (876) 839-2056 | H3: Single Payment | I3: 220 | J3: - | K3: - | L3: - | M3: Full | N3: 150 | O3: =SUM(I3:L3) -> 220 | P3: =O3-(O3*$T$4)+N3 -> 348 | Q3: =P3*$T$5 -> 53908.68 | S3: Interest | T3: 0.15
A4: 30008 | B4: Laim | C4: Johnson | D4: 32 | E4: Male | F4: 456 Oak Avenue, Lakeside | G4: (876) 475-8123 | H4: Installment | I4: - | J4: 73.33 | K4: - | L4: - | M4: Partial | N4: 50 | O4: =SUM(I4:L4) -> 73.33 | P4: =O4+(O4*$T$3)+N4 -> 134.3295 | Q4: =P4*$T$5 -> 20808.983 | S4: Discount | T4: 0.1
A5: 30002 | B5: Olivia | C5: Williams | D5: 19 | E5: Female | F5: 789 Elm Lane, Greenfield | G5: (876) 921-6347 | H5: Single Payment | I5: 220 | J5: - | K5: - | L5: - | M5: Partial | N5: 50 | O5: =SUM(I5:L5) -> 220 | P5: =O5-(O5*$T$4)+N5 -> 248 | Q5: =P5*$T$5 -> 38417.68 | S5: JMD Equivalent | T5: 154.91
A6: 30003 | B6: Noah | C6: Jones | D6: 42 | E6: Male | F6: 101 Pine Road, Hilltop | G6: (876) 568-9743 | H6: Single Payment | I6: 220 | J6: - | K6: - | L6: - | M6: Partial | N6: 50 | O6: =SUM(I6:L6) -> 220 | P6: =O6-(O6*$T$4)+N6 -> 248 | Q6: =P6*$T$5 -> 38417.68
A7: 30009 | B7: Ava | C7: Brown | D7: 37 | E7: Female | F7: 234 Cedar Court, Riverside | G7: (876) 987-5432 | H7: Installment | I7: - | J7: 73.33 | K7: 73.33 | L7: - | M7: Full | N7: 150 | O7: =SUM(I7:L7) -> 146.66 | P7: =O7+(O7*$T$3)+N7 -> 318.659 | Q7: =P7*$T$5 -> 49363.466
A8: 30010 | B8: William | C8: Davis | D8: 20 | E8: Male | F8: 567 Birch Drive, Meadowbrook | G8: (876) 314-1592 | H8: Installment | I8: - | J8: 73.33 | K8: 73.33 | L8: 73.33 | M8: Full | N8: 150 | O8: =SUM(I8:L8) -> 219.99 | P8: =O8+(O8*$T$3)+N8 -> 402.9885 | Q8: =P8*$T$5 -> 62426.949
A9: 30011 | B9: Sophia | C9: Mille | D9: 29 | E9: Female | F9: 890 Walnut Avenue, Woodland | G9: (876) 246-8013 | H9: Installment | I9: - | J9: - | K9: - | L9: - | M9: Partial | N9: 50 | O9: =SUM(I9:L9) -> 0 | P9: =O9+(O9*$T$3)+N9 -> 50 | Q9: =P9*$T$5 -> 7745.5
A10: 30012 | B10: James | C10: Wilson | D10: 36 | E10: Male | F10: 112 Oakwood Circle, Lakeshore | G10: (876) 756-4213 | H10: Installment | I10: - | J10: 73.33 | K10: - | L10: - | M10: Partial | N10: 50 | O10: =SUM(I10:L10) -> 73.33 | P10: =O10+(O10*$T$3)+N10 -> 134.3295 | Q10: =P10*$T$5 -> 20808.983
A11: 30004 | B11: Isabella | C11: Moore | D11: 23 | E11: Female | F11: 345 Maple Lane, Forest Hills | G11: (876) 999-7683 | H11: Single Payment | I11: 220 | J11: - | K11: - | L11: - | M11: Partial | N11: 50 | O11: =SUM(I11:L11) -> 220 | P11: =O11-(O11*$T$4)+N11 -> 248 | Q11: =P11*$T$5 -> 38417.68
A12: 30005 | B12: Oliver | C12: Taylor | D12: 40 | E12: Male | F12: 678 Pinecrest Road, Mountain View | G12: (876) 830-7595 | H12: Single Payment | I12: 220 | J12: - | K12: - | L12: - | M12: Full | N12: 150 | O12: =SUM(I12:L12) -> 220 | P12: =O12-(O12*$T$4)+N12 -> 348 | Q12: =P12*$T$5 -> 53908.68
A13: 30006 | B13: Mia | C13: Anderson | D13: 18 | E13: Female | F13: 911 Elm Street, Parkside | G13: (876) 194-0004 | H13: Single Payment | I13: 220 | J13: - | K13: - | L13: - | M13: Partial | N13: 50 | O13: =SUM(I13:L13) -> 220 | P13: =O13-(O13*$T$4)+N13 -> 248 | Q13: =P13*$T$5 -> 38417.68
A14: 30007 | B14: Benjamin | C14: Thomas | D14: 34 | E14: Male | F14: 1313 Birchwood Avenue, Lakeview | G14: (876) 224-6959 | H14: Installment | I14: - | J14: 73.33 | K14: 73.33 | L14: - | M14: Partial | N14: 50 | O14: =SUM(I14:L14) -> 146.66 | P14: =O14+(O14*$T$3)+N14 -> 218.659 | Q14: =P14*$T$5 -> 33872.466
A15: 30013 | B15: Charlotte | C15: Jackson | D15: 27 | E15: Female | F15: 1414 Willow Way, Brookside | G15: (876) 984-1164 | H15: Single Payment | I15: 220 | J15: - | K15: - | L15: - | M15: Partial | N15: 50 | O15: =SUM(I15:L15) -> 220 | P15: =O15-(O15*$T$4)+N15 -> 248 | Q15: =P15*$T$5 -> 38417.68
A16: 30014 | B16: Elijah | C16: White | D16: 48 | E16: Male | F16: 1515 Cedar Lane, Hillcrest | G16: (876) 152-5005 | H16: Single Payment | I16: 220 | J16: - | K16: - | L16: - | M16: Full | N16: 150 | O16: =SUM(I16:L16) -> 220 | P16: =O16-(O16*$T$4)+N16 -> 348 | Q16: =P16*$T$5 -> 53908.68
A17: 30015 | B17: Amelia | C17: Harris | D17: 22 | E17: Female | F17: 1618 Oakwood Drive, Lakeside | G17: (876) 323-5372 | H17: Single Payment | I17: 220 | J17: - | K17: - | L17: - | M17: Partial | N17: 50 | O17: =SUM(I17:L17) -> 220 | P17: =O17-(O17*$T$4)+N17 -> 248 | Q17: =P17*$T$5 -> 38417.68
A19: No. of Masqueraders | C19: =COUNT(A3:A17) -> 15 | O19: Total Payment Collected | P19: =SUM(P3:P17) -> 3790.9655 | Q19: =SUM(Q3:Q17) -> 587258.47
A20: Total Costume Payment | C20: =SUM(O3:O17) -> 2639.97
A21: Total Inclusive Fee | C21: =SUMIF(N3:N17,"=150") -> 750
A22: Total Overall Payment | C22: =SUM(P3:P17) -> 3790.9655
A24: EXPENDITURE
A25: Service | B25: Cost Per Person | C25: Flat Rate | D25: Service Interest | E25: Total Cost | F25: Total Cost per Service
A26: Food | B26: 60 | C26: - | D26: 0.15 | E26: =(B26+(B26*D26)) -> 69 | F26: =PRODUCT(E26*$C$19) -> 1035
A27: Drink | B27: 40 | C27: - | D27: 0.15 | E27: =(B27+(B27*D27)) -> 46 | F27: =PRODUCT(E27*$C$19) -> 690
A28: Material | B28: 150 | C28: - | D28: 0.12 | E28: =(B28+(B28*D28)) -> 168 | F28: =PRODUCT(E28*$C$19) -> 2520
A29: Labour | B29: 75 | C29: - | D29: 0.08 | E29: =(B29+(B29*D29)) -> 81 | F29: =PRODUCT(E29*$C$19) -> 1215
A30: Bathroom | B30: - | C30: 3000 | D30: - | E30: =C30/5 -> 600 | F30: =PRODUCT(E30,15) -> 9000
A31: Transort | B31: - | C31: 2500 | D31: - | E31: =C31/5 -> 500 | F31: =PRODUCT(E31,15) -> 7500
A32: Music | B32: - | C32: 4000 | D32: - | E32: =C32/5 -> 800 | F32: =PRODUCT(E32,15) -> 12000
A33: Security | B33: - | C33: 1800 | D33: - | E33: =C33/5 -> 360 | F33: =PRODUCT(E33,15) -> 5400
A34: Artiste | B34: - | C34: 5000 | D34: - | E34: =C34/5 -> 1000 | F34: =PRODUCT(E34,15) -> 15000
E36: Total Expenditure | F36: =SUM(F26:F34) -> 54360

Sheet JamCam X
A1: Income
A2: ID Number | B2: First name | C2: Last Name | D2: Age | E2: Gender | F2: Address | G2: Phone Number | H2: Costume Payment Option | I2: Full Payment | J2: Installments | M2: Inclusive Fee Option | O2: Total Costume Amount | P2: Total Payment in USD | Q2: Total Payment in JMD
A3: 40001 | B3: Bryan | C3: Wallace | D3: 34 | E3: Male | F3: 4 Molynes Rd, Kingston 10 | G3: (876) 926-4569 | H3: Single Payment | I3: 280 | J3: - | K3: - | L3: - | M3: Full | N3: 150 | O3: =SUM(I3:L3) -> 280 | P3: =O3-(O3*$T$4)+N3 -> 388 | Q3: =P3*$T$5 -> 60105.08 | S3: Interest | T3: 0.1
A4: 40002 | B4: John | C4: Brown | D4: 23 | E4: Male | F4: 16 Seymour Avenue, Kingston 6 | G4: (876) 927-3790 | H4: Single Payment | I4: 280 | J4: - | K4: - | L4: - | M4: Full | N4: 150 | O4: =SUM(I4:L4) -> 280 | P4: =O4-(O4*$T$4)+N4 -> 388 | Q4: =P4*$T$5 -> 60105.08 | S4: Discount | T4: 0.15
A5: 40003 | B5: Mekae | C5: Wilson | D5: 32 | E5: Female | F5: 9 Easton Avenue, Kingston 5 | G5: (876) 927-3688 | H5: Single Payment | I5: 280 | J5: - | K5: - | L5: - | M5: Partial | N5: 50 | O5: =SUM(I5:L5) -> 280 | P5: =O5-(O5*$T$4)+N5 -> 288 | Q5: =P5*$T$5 -> 44614.08 | S5: JMD Equivalent | T5: 154.91
A6: 40007 | B6: Alexander | C6: Wyclifee | D6: 26 | E6: Male | F6: 85 Hagley Park Rd, Kingston 10 | G6: (876) 960-3971 | H6: Installment | I6: - | J6: 93.33 | K6: - | L6: - | M6: Full | N6: 150 | O6: =SUM(I6:L6) -> 93.33 | P6: =O6+(O6*$T$3)+N6 -> 252.663 | Q6: =P6*$T$5 -> 39140.025
A7: 40008 | B7: Deshawn | C7: Smith | D7: 43 | E7: Male | F7: 30 Dunrobin Avenue, Kingston 10 | G7: 876 755-3678 | H7: Installment | I7: - | J7: 93.33 | K7: 93.33 | L7: 93.33 | M7: Full | N7: 150 | O7: =SUM(I7:L7) -> 279.99 | P7: =O7+(O7*$T$3)+N7 -> 457.989 | Q7: =P7*$T$5 -> 70947.076
A8: 40009 | B8: Devontae | C8: Bryant | D8: 45 | E8: Male | F8: 72 Hope Rd, Kingston 6 | G8: (876) 927-3221 | H8: Single Payment | I8: 280 | J8: - | K8: - | L8: - | M8: Partial | N8: 50 | O8: =SUM(I8:L8) -> 280 | P8: =O8-(O8*$T$4)+N8 -> 288 | Q8: =P8*$T$5 -> 44614.08
A9: 40004 | B9: Ana | C9: Warming | D9: 22 | E9: Female | F9: 53 Knutsford Blvd, Kingston 12 | G9: (876) 926-8911 | H9: Single Payment | I9: 280 | J9: - | K9: - | L9: - | M9: Partial | N9: 50 | O9: =SUM(I9:L9) -> 280 | P9: =O9-(O9*$T$4)+N9 -> 288 | Q9: =P9*$T$5 -> 44614.08
A10: 40005 | B10: Jenna | C10: Smalling | D10: 34 | E10: Female | F10: 87a Orange St., Kingston | G10: (876) 924-9187 | H10: Installment | I10: - | J10: 93.33 | K10: - | L10: - | M10: Full | N10: 150 | O10: =SUM(I10:L10) -> 93.33 | P10: =O10+(O10*$T$3)+N10 -> 252.663 | Q10: =P10*$T$5 -> 39140.025
A11: 40010 | B11: Rebecca | C11: Porter | D11: 23 | E11: Female | F11: 12 Ruthven Rd, Kingston 10 | G11: (876) 968-8396 | H11: Installment | I11: - | J11: 93.33 | K11: 93.33 | L11: - | M11: Full | N11: 150 | O11: =SUM(I11:L11) -> 186.66 | P11: =O11+(O11*$T$3)+N11 -> 355.326 | Q11: =P11*$T$5 -> 55043.551
A12: 40011 | B12: Aji | C12: Ferguson | D12: 23 | E12: Male | F12: Wentworth, St. Mary | G12: (876) 879-3196 | H12: Installment | I12: - | J12: 93.33 | K12: - | L12: - | M12: Partial | N12: 50 | O12: =SUM(I12:L12) -> 93.33 | P12: =O12+(O12*$T$3)+N12 -> 152.663 | Q12: =P12*$T$5 -> 23649.025
A13: 40012 | B13: Mikealia | C13: Holness | D13: 29 | E13: Female | F13: 123 Constant Spring Rd, Kingston 8 | G13: (876) 924-1656 | H13: Installment | I13: - | J13: 93.33 | K13: 93.33 | L13: 93.33 | M13: Full | N13: 150 | O13: =SUM(I13:L13) -> 279.99 | P13: =O13+(O13*$T$3)+N13 -> 457.989 | Q13: =P13*$T$5 -> 70947.076
A14: 40006 | B14: Sabrina | C14: Patrick | D14: 30 | E14: Female | F14: 14 Half Retirement Rd, Kingston | G14: (876) 968-0826 | H14: Single Payment | I14: 280 | J14: - | K14: - | L14: - | M14: Full | N14: 150 | O14: =SUM(I14:L14) -> 280 | P14: =O14-(O14*$T$4)+N14 -> 388 | Q14: =P14*$T$5 -> 60105.08
A15: 40013 | B15: Ryan | C15: Lewis | D15: 32 | E15: Male | F15: 21 Red Hills Rd, Kingston 10 | G15: (876) 960-2456 | H15: Single Payment | I15: 280 | J15: - | K15: - | L15: - | M15: Full | N15: 150 | O15: =SUM(I15:L15) -> 280 | P15: =O15-(O15*$T$4)+N15 -> 388 | Q15: =P15*$T$5 -> 60105.08
A16: 40014 | B16: Luke | C16: Gordan | D16: 19 | E16: Male | F16: 24 Riverton Blvd, Kingstion | G16: (876) 923-8666 | H16: Single Payment | I16: 280 | J16: - | K16: - | L16: - | M16: Full | N16: 150 | O16: =SUM(I16:L16) -> 280 | P16: =O16-(O16*$T$4)+N16 -> 388 | Q16: =P16*$T$5 -> 60105.08
A17: 40015 | B17: Shericka | C17: Blake | D17: 39 | E17: Female | F17: 10 Trafalgar Rd, Kingston 5 | G17: (876) 978-3049 | H17: Single Payment | I17: 280 | J17: - | K17: - | L17: - | M17: Full | N17: 150 | O17: =SUM(I17:L17) -> 280 | P17: =O17-(O17*$T$4)+N17 -> 388 | Q17: =P17*$T$5 -> 60105.08
A19: No. of Masqueraders | C19: =COUNT(A2:A17) -> 15 | O19: Total Payment Collected | P19: =SUM(P3:P17) -> 5121.293 | Q19: =SUM(Q3:Q17) -> 793339.5
A20: Total Costume Payment | C20: =SUM(O3:O17) -> 3546.63
A21: Total Inclusive Fee | C21: =SUMIF(N3:N17,"=150") -> 1650
A22: Total Overall Payment | C22: =SUM(P3:P17) -> 5121.293
A24: EXPENDITURE
A25: Service | B25: Cost Per Person | C25: Flat Rate | D25: Service Interest | E25: Total Cost | F25: Total Cost per Service
A26: Food | B26: 60 | C26: - | D26: 0.15 | E26: ='Xod-Us'!E26*D26+'Xod-Us'!E26 -> 79.35 | F26: =PRODUCT(E26,15) -> 1190.25
A27: Drink | B27: 40 | C27: - | D27: 0.15 | E27: ='Xod-Us'!E27*D27+'Xod-Us'!E27 -> 52.9 | F27: =PRODUCT(E27,15) -> 793.5
A28: Material | B28: 150 | C28: - | D28: 0.12 | E28: ='Xod-Us'!E28*D28+'Xod-Us'!E28 -> 188.16 | F28: =PRODUCT(E28,15) -> 2822.4
A29: Labour | B29: 75 | C29: - | D29: 0.08 | E29: ='Xod-Us'!E29*D29+'Xod-Us'!E29 -> 87.48 | F29: =PRODUCT(E29,15) -> 1312.2
A30: Bathroom | B30: - | C30: 3000 | D30: - | E30: =C30/5 -> 600 | F30: =PRODUCT(E30,15) -> 9000
A31: Transort | B31: - | C31: 2500 | D31: - | E31: =C31/5 -> 500 | F31: =PRODUCT(E31,15) -> 7500
A32: Music | B32: - | C32: 4000 | D32: - | E32: =C32/5 -> 800 | F32: =PRODUCT(E32,15) -> 12000
A33: Security | B33: - | C33: 1800 | D33: - | E33: =C33/5 -> 360 | F33: =PRODUCT(E33,15) -> 5400
A34: Artiste | B34: - | C34: 5000 | D34: - | E34: =C34/5 -> 1000 | F34: =PRODUCT(E34,15) -> 15000
E36: Total Expenditure | F36: =SUM(F26:F34) -> 55018.35

Sheet Fant-X
A1: Income
A2: ID Number | B2: First name | C2: Last Name | D2: Age | E2: Gender | F2: Address | G2: Phone Number | H2: Costume Payment Option | I2: Full Payment | J2: Installments | M2: Inclusive Fee Option | O2: Total Costume Amount | P2: Total Payment in USD | Q2: Total Payment in JMD
A3: 50012 | B3: Emma | C3: Johnson | D3: 32 | E3: Female | F3: 63 Mark Lane, Kingston | G3: (876) 967-0911 | H3: Installment | I3: - | J3: 116.7 | K3: 116.7 | L3: - | M3: Partial | N3: 50 | O3: =SUM(I3:L3) -> 233.4 | P3: =O3+(O3*$T$3)+N3 -> 306.74 | Q3: =P3*$T$5 -> 47517.093 | S3: Interest | T3: 0.1
A4: 50013 | B4: Liam | C4: Patel | D4: 25 | E4: Male | F4: 7 Lady Musgrave Rd, Kingston | G4: (876) 927-5626 | H4: Installment | I4: - | J4: 116.7 | K4: 116.7 | L4: 116.7 | M4: Partial | N4: 50 | O4: =SUM(I4:L4) -> 350.1 | P4: =O4+(O4*$T$3)+N4 -> 435.11 | Q4: =P4*$T$5 -> 67402.89 | S4: Discount | T4: 0.15
A5: 50005 | B5: Olivia | C5: Nguyen | D5: 43 | E5: Female | F5: 5 Manchester Rd, Mandeville | G5: (876) 926-2956 | H5: Single Payment | I5: 350 | J5: - | K5: - | L5: - | M5: Full | N5: 150 | O5: =SUM(I5:L5) -> 350 | P5: =O5-(O5*$T$4)+N5 -> 447.5 | Q5: =P5*$T$5 -> 69322.225 | S5: JMD Equivalent | T5: 154.91
A6: 50014 | B6: Noah | C6: Smith | D6: 19 | E6: Male | F6: 71 Molynes Rd, Kingston 10 | G6: (876) 758-8099 | H6: Installment | I6: - | J6: 116.7 | K6: 116.7 | L6: 116.7 | M6: Full | N6: 150 | O6: =SUM(I6:L6) -> 350.1 | P6: =O6+(O6*$T$3)+N6 -> 535.11 | Q6: =P6*$T$5 -> 82893.89
A7: 50006 | B7: Sophia | C7: Brown | D7: 38 | E7: Female | F7: Twickenham Pk, Spanish Town | G7: (876) 984-3092 | H7: Single Payment | I7: 350 | J7: - | K7: - | L7: - | M7: Partial | N7: 50 | O7: =SUM(I7:L7) -> 350 | P7: =O7-(O7*$T$4)+N7 -> 347.5 | Q7: =P7*$T$5 -> 53831.225
A8: 50007 | B8: Ava | C8: Garcia | D8: 51 | E8: Female | F8: 2 Molynes Rd, Kingston 10 | G8: (876) 923-7285 | H8: Single Payment | I8: 350 | J8: - | K8: - | L8: - | M8: Partial | N8: 50 | O8: =SUM(I8:L8) -> 350 | P8: =O8-(O8*$T$4)+N8 -> 347.5 | Q8: =P8*$T$5 -> 53831.225
A9: 50008 | B9: Ethan | C9: Williams | D9: 27 | E9: Male | F9: 327a Spanish Town Rd, Kingston 11 | G9: (876) 901-5218 | H9: Single Payment | I9: 350 | J9: - | K9: - | L9: - | M9: Full | N9: 150 | O9: =SUM(I9:L9) -> 350 | P9: =O9-(O9*$T$4)+N9 -> 447.5 | Q9: =P9*$T$5 -> 69322.225
A10: 50015 | B10: Isabella | C10: Lee | D10: 36 | E10: Female | F10: 8 Haughton Ave, Kingston 5 | G10: (876) 906-1033 | H10: Installment | I10: - | J10: 116.7 | K10: - | L10: - | M10: Full | N10: 150 | O10: =SUM(I10:L10) -> 116.7 | P10: =O10+(O10*$T$3)+N10 -> 278.37 | Q10: =P10*$T$5 -> 43122.297
A11: 50009 | B11: Lucas | C11: Rodriguez | D11: 22 | E11: Male | F11: Upr Elletson Rd, Kingston 16 | G11: (876) 928-1024 | H11: Single Payment | I11: 350 | J11: - | K11: - | L11: - | M11: Full | N11: 150 | O11: =SUM(I11:L11) -> 350 | P11: =O11+(O11*$T$3)+N11 -> 535 | Q11: =P11*$T$5 -> 82876.85
A12: 50001 | B12: Charlotte | C12: Martinez | D12: 47 | E12: Female | F12: 3 Duke St., Kingston | G12: (876) 922-6150 | H12: Installment | I12: - | J12: 116.7 | K12: 116.7 | L12: 116.7 | M12: Partial | N12: 50 | O12: =SUM(I12:L12) -> 350.1 | P12: =O12+(O12*$T$3)+N12 -> 435.11 | Q12: =P12*$T$5 -> 67402.89
A13: 50002 | B13: Mia | C13: Clark | D13: 30 | E13: Female | F13: 51 Gilmour Drive, Kingston | G13: (876) 924-5291 | H13: Installment | I13: - | J13: 116.7 | K13: 116.7 | L13: - | M13: Partial | N13: 50 | O13: =SUM(I13:L13) -> 233.4 | P13: =O13+(O13*$T$3)+N13 -> 306.74 | Q13: =P13*$T$5 -> 47517.093
A14: 50003 | B14: James | C14: Taylor | D14: 56 | E14: Male | F14: 39 Caracas Ave, Kingston 15 | G14: (876) 923-6894 | H14: Installment | I14: - | J14: 116.7 | K14: 116.7 | L14: - | M14: Partial | N14: 50 | O14: =SUM(I14:L14) -> 233.4 | P14: =O14+(O14*$T$3)+N14 -> 306.74 | Q14: =P14*$T$5 -> 47517.093
A15: 50004 | B15: Mason | C15: Martinez | D15: 41 | E15: Male | F15: Gordon Town, Kingston 7 | G15: (876) 702-1866 | H15: Installment | I15: - | J15: 116.7 | K15: 116.7 | L15: - | M15: Full | N15: 150 | O15: =SUM(I15:L15) -> 233.4 | P15: =O15+(O15*$T$3)+N15 -> 406.74 | Q15: =P15*$T$5 -> 63008.093
A16: 50010 | B16: Elijah | C16: Scott | D16: 29 | E16: Male | F16: 53 Gilmour Dr, Kingston 20 | G16: (876) 925-4570 | H16: Single Payment | I16: 350 | J16: - | K16: - | L16: - | M16: Full | N16: 150 | O16: =SUM(I16:L16) -> 350 | P16: =O16-(O16*$T$4)+N16 -> 447.5 | Q16: =P16*$T$5 -> 69322.225
A17: 50011 | B17: Amelia | C17: Anderson | D17: 34 | E17: Female | F17: 25 East Gueen St, Kingston | G17: (876) 922-6983 | H17: Single Payment | I17: 350 | J17: - | K17: - | L17: - | M17: Partial | N17: 50 | O17: =SUM(I17:L17) -> 350 | P17: =O17-(O17*$T$4)+N17 -> 347.5 | Q17: =P17*$T$5 -> 53831.225
A19: No. of Masqueraders | C19: =COUNT(A2:A17) -> 15 | O19: Total Payment Collected | P19: =SUM(P3:P17) -> 5930.66 | Q19: =SUM(Q3:Q17) -> 918718.54
A20: Total Costume Payment | C20: =SUM(O3:O17) -> 4550.6
A21: Total Inclusive Fee | C21: =SUMIF(N3:N17,"=150") -> 1050
A22: Total Overall Payment | C22: =SUM(P3:P17) -> 5930.66
A24: EXPENDITURE
A25: Service | B25: Cost Per Person | C25: Flat Rate | D25: Service Interest | E25: Total Cost | F25: Total Cost per Service
A26: Food | B26: 60 | C26: - | D26: 0.15 | E26: ='JamCam X'!E26*D26+'JamCam X'!E26 -> 91.2525 | F26: =PRODUCT(E26,15) -> 1368.7875
A27: Drink | B27: 40 | C27: - | D27: 0.15 | E27: ='JamCam X'!E27*D27+'JamCam X'!E27 -> 60.835 | F27: =PRODUCT(E27,15) -> 912.525
A28: Material | B28: 150 | C28: - | D28: 0.12 | E28: ='JamCam X'!E28*D28+'JamCam X'!E28 -> 210.7392 | F28: =PRODUCT(E28,15) -> 3161.088
A29: Labour | B29: 75 | C29: - | D29: 0.08 | E29: ='JamCam X'!E29*D29+'JamCam X'!E29 -> 94.4784 | F29: =PRODUCT(E29,15) -> 1417.176
A30: Bathroom | B30: - | C30: 3000 | D30: - | E30: =C30/5 -> 600 | F30: =PRODUCT(E30,15) -> 9000
A31: Transort | B31: - | C31: 2500 | D31: - | E31: =C31/5 -> 500 | F31: =PRODUCT(E31,15) -> 7500
A32: Music | B32: - | C32: 4000 | D32: - | E32: =C32/5 -> 800 | F32: =PRODUCT(E32,15) -> 12000
A33: Security | B33: - | C33: 1800 | D33: - | E33: =C33/5 -> 360 | F33: =PRODUCT(E33,15) -> 5400
A34: Artiste | B34: - | C34: 5000 | D34: - | E34: =C34/5 -> 1000 | F34: =PRODUCT(E34,15) -> 15000
E36: Total Expenditure | F36: =SUM(F26:F34) -> 55759.576

Sheet DreamX
A1: Income
A2: ID Number | B2: First name | C2: Last Name | D2: Age | E2: Gender | F2: Address | G2: Phone Number | H2: Costume Payment Option | I2: Full Payment | J2: Installments | M2: Inclusive Fee Option | O2: Total Costume Amount | P2: Total Payment in USD | Q2: Total Payment in JMD
A3: 60009 | B3: Benjamin | C3: White | D3: 32 | E3: Male | F3: 4 Dunrobin Ave, Kingston 10 | G3: (876) 925-4745 | H3: Single Payment | I3: 425 | J3: - | K3: - | L3: - | M3: Partial | N3: 50 | O3: =SUM(I3:L3) -> 425 | P3: =O3-(O3*$T$4)+N3 -> 411.25 | Q3: =P3*$T$5 -> 63706.737 | S3: Interest | T3: 0.1
A4: 60010 | B4: Grace | C4: Thompson | D4: 27 | E4: Female | F4: 1/2 Munroe Rd, Kingston 6 | G4: (876) 927-7364 | H4: Single Payment | I4: 425 | J4: - | K4: - | L4: - | M4: Full | N4: 150 | O4: =SUM(I4:L4) -> 425 | P4: =O4-(O4*$T$4)+N4 -> 511.25 | Q4: =P4*$T$5 -> 79197.738 | S4: Discount | T4: 0.15
A5: 60011 | B5: Lucas | C5: Carter | D5: 35 | E5: Male | F5: 47d Old Hope Rd, Kingston 5 | G5: (876) 927-8491 | H5: Single Payment | I5: 425 | J5: - | K5: - | L5: - | M5: Full | N5: 150 | O5: =SUM(I5:L5) -> 425 | P5: =O5-(O5*$T$4)+N5 -> 511.25 | Q5: =P5*$T$5 -> 79197.738 | S5: JMD Equivalent | T5: 154.91
A6: 20011 | B6: Harper | C6: Lee | D6: 29 | E6: Female | F6: 6 Caledonia Ave, Kingston 5 | G6: (876) 929-6666 | H6: Installment | I6: - | J6: 141.7 | K6: 141.7 | L6: - | M6: Full | N6: 150 | O6: =SUM(I6:L6) -> 283.4 | P6: =O3+(O3*$T$3)+N3 -> 517.5 | Q6: =P6*$T$5 -> 80165.925
A7: 30013 | B7: Daniel | C7: Nguyen | D7: 41 | E7: Male | F7: 4 Goodwood Terr, Kingston 10 | G7: (876) 135-6924 | H7: Single Payment | I7: 425 | J7: - | K7: - | L7: - | M7: Partial | N7: 50 | O7: =SUM(I7:L7) -> 425 | P7: =O7-(O7*$T$4)+N7 -> 411.25 | Q7: =P7*$T$5 -> 63706.737
A8: 60004 | B8: Lily | C8: Parker | D8: 24 | E8: Female | F8: 136a Red Hills Rd, Kingston | G8: (876) 931-8321 | H8: Installment | I8: - | J8: 141.7 | K8: 141.7 | L8: 141.7 | M8: Full | N8: 150 | O8: =SUM(I8:L8) -> 425.1 | P8: =O8+(O8*$T$3)+N8 -> 617.61 | Q8: =P8*$T$5 -> 95673.965
A9: 60005 | B9: Gabriel | C9: Robinson | D9: 38 | E9: Female | F9: 22a Union St, Montego Bay | G9: (876) 979-0068 | H9: Installment | I9: - | J9: 141.7 | K9: 141.7 | L9: 141.7 | M9: Full | N9: 150 | O9: =SUM(I9:L9) -> 425.1 | P9: =O9+(O9*$T$3)+N9 -> 617.61 | Q9: =P9*$T$5 -> 95673.965
A10: 40013 | B10: Chloe | C10: Adams | D10: 30 | E10: Female | F10: White Marl, St. Catherine | G10: (876) 984-2740 | H10: Single Payment | I10: 425 | J10: - | K10: - | L10: - | M10: Full | N10: 150 | O10: =SUM(I10:L10) -> 425 | P10: =O10-(O10*$T$4)+N10 -> 511.25 | Q10: =P10*$T$5 -> 79197.738
A11: 60006 | B11: Samuel | C11: Wright | D11: 33 | E11: Male | F11: 1 Kent Ave, Montego Bay | G11: (876) 952-4376 | H11: Installment | I11: - | J11: 141.7 | K11: 141.7 | L11: 141.7 | M11: Partial | N11: 50 | O11: =SUM(I11:L11) -> 425.1 | P11: =O11+(O11*$T$3)+N11 -> 517.61 | Q11: =P11*$T$5 -> 80182.965
A12: 60008 | B12: Zoe | C12: Mitchell | D12: 26 | E12: Female | F12: Spur Tree, Mandeville | G12: (876) 962-2213 | H12: Installment | I12: - | J12: 141.7 | K12: - | L12: - | M12: Full | N12: 150 | O12: =SUM(I12:L12) -> 141.7 | P12: =O12+(O12*$T$3)+N12 -> 305.87 | Q12: =P12*$T$5 -> 47382.322
A13: 60007 | B13: Elijah | C13: Baker | D13: 37 | E13: Male | F13: Church rd, Bog Walk | G13: (876) 929-3079 | H13: Installment | I13: - | J13: 141.7 | K13: - | L13: - | M13: Partial | N13: 50 | O13: =SUM(I13:L13) -> 141.7 | P13: =O13+(O13*$T$3)+N13 -> 205.87 | Q13: =P13*$T$5 -> 31891.322
A14: 40014 | B14: Ruby | C14: Foster | D14: 22 | E14: Female | F14: 59 Lyndhurst Rd, Kingston 5 | G14: (876) 985-2014 | H14: Single Payment | I14: 425 | J14: - | K14: - | L14: - | M14: Full | N14: 150 | O14: =SUM(I14:L14) -> 425 | P14: =O14-(O14*$T$4)+N14 -> 511.25 | Q14: =P14*$T$5 -> 79197.738
A15: 60001 | B15: Jacob | C15: Stewart | D15: 40 | E15: Male | F15: 14 Ballater Ave, Kingston 10 | G15: (876) 968-4935 | H15: Single Payment | I15: 425 | J15: - | K15: - | L15: - | M15: Full | N15: 150 | O15: =SUM(I15:L15) -> 425 | P15: =O15-(O15*$T$4)+N15 -> 511.25 | Q15: =P15*$T$5 -> 79197.738
A16: 60002 | B16: Madison | C16: Hill | D16: 28 | E16: Female | F16: 3 Beechwood Ave, Kingston 5 | G16: (876) 929-1480 | H16: Single Payment | I16: 425 | J16: - | K16: - | L16: - | M16: Partial | N16: 50 | O16: =SUM(I16:L16) -> 425 | P16: =O16-(O16*$T$4)+N16 -> 411.25 | Q16: =P16*$T$5 -> 63706.737
A17: 60003 | B17: Imani | C17: Bennett | D17: 36 | E17: Female | F17: 58 HWT Rd, Kingston 10 | G17: (876) 929-8496 | H17: Single Payment | I17: 425 | J17: - | K17: - | L17: - | M17: Partial | N17: 50 | O17: =SUM(I17:L17) -> 425 | P17: =O17-(O17*$T$4)+N17 -> 411.25 | Q17: =P17*$T$5 -> 63706.737
A19: No. of Masqueraders | C19: =COUNT(A2:A17) -> 15 | O19: Total Payment Collected | P19: =SUM(P3:P17) -> 6983.32 | Q19: =SUM(Q3:Q17) -> 1081786.1
A20: Total Costume Payment | C20: =SUM(O3:O17) -> 5667.1
A21: Total Inclusive Fee | C21: =SUMIF(N3:N17,"=150") -> 1350
A22: Total Overall Payment | C22: =SUM(P3:P17) -> 6983.32
A24: EXPENDITURE
A25: Service | B25: Cost Per Person | C25: Flat Rate | D25: Service Interest | E25: Total Cost | F25: Total Cost per Service
A26: Food | B26: 60 | C26: - | D26: 0.15 | E26: ='Fant-X'!E26*D26+'Fant-X'!E26 -> 104.94038 | F26: =PRODUCT(E26,15) -> 1574.1056
A27: Drink | B27: 40 | C27: - | D27: 0.15 | E27: ='Fant-X'!E27*D27+'Fant-X'!E27 -> 69.96025 | F27: =PRODUCT(E27,15) -> 1049.4037
A28: Material | B28: 150 | C28: - | D28: 0.12 | E28: ='Fant-X'!E28*D28+'Fant-X'!E28 -> 236.0279 | F28: =PRODUCT(E28,15) -> 3540.4186
A29: Labour | B29: 75 | C29: - | D29: 0.08 | E29: ='Fant-X'!E29*D29+'Fant-X'!E29 -> 102.03667 | F29: =PRODUCT(E29,15) -> 1530.5501
A30: Bathroom | B30: - | C30: 3000 | D30: - | E30: =C30/5 -> 600 | F30: =PRODUCT(E30,15) -> 9000
A31: Transort | B31: - | C31: 2500 | D31: - | E31: =C31/5 -> 500 | F31: =PRODUCT(E31,15) -> 7500
A32: Music | B32: - | C32: 4000 | D32: - | E32: =C32/5 -> 800 | F32: =PRODUCT(E32,15) -> 12000
A33: Security | B33: - | C33: 1800 | D33: - | E33: =C33/5 -> 360 | F33: =PRODUCT(E33,15) -> 5400
A34: Artiste | B34: - | C34: 5000 | D34: - | E34: =C34/5 -> 1000 | F34: =PRODUCT(E34,15) -> 15000
E36: Total Expenditure | F36: =SUM(F26:F34) -> 56594.478
